LICENSE
README.md
pyproject.toml
setup.py
Classeviva.py.egg-info/PKG-INFO
Classeviva.py.egg-info/SOURCES.txt
Classeviva.py.egg-info/dependency_links.txt
Classeviva.py.egg-info/requires.txt
Classeviva.py.egg-info/top_level.txt
src/classeviva/__init__.py
src/classeviva/__main__.py
src/classeviva/main.py
src/classeviva/collegamenti/__init__.py
src/classeviva/collegamenti/collegamenti.py
src/classeviva/eccezioni/__init__.py
src/classeviva/eccezioni/eccezioni.py
src/classeviva/variabili/__init__.py
src/classeviva/variabili/variabili.py