Metadata-Version: 2.1
Name: Classeviva.py
Version: 1.2.7
Summary: Classeviva Python API wrapper
Home-page: https://github.com/Lioydiano/Classeviva
Download-URL: https://github.com/Lioydiano/Classeviva/archive/refs/tags/v1.2.7.tar.gz
Author: FLAK-ZOSO
Author-email: mattia.marchese.2006@gmail.com
License: MIT
Keywords: classeviva,api
Classifier: Programming Language :: Python :: 3
Classifier: Programming Language :: Python :: 3.10
Classifier: Programming Language :: Python :: Implementation :: CPython
Classifier: Development Status :: 3 - Alpha
Classifier: License :: OSI Approved :: MIT License
Classifier: Operating System :: OS Independent
Classifier: Intended Audience :: Developers
Classifier: Natural Language :: Italian
Classifier: Natural Language :: English
Classifier: Typing :: Typed
Requires: requests
Requires-Python: >=3.10
License-File: LICENSE
